Metadata-Version: 2.4
Name: terraform-it
Version: 0.2.1
Summary: A tool to generate Terraform providers from OpenAPI specs and Go SDKs.
Home-page: https://github.com/Deep070203/terraform-it
Author: Deep Shah
Author-email: shahdeep855@gmail.com
Classifier: Programming Language :: Python :: 3
Classifier: License :: OSI Approved :: MIT License
Classifier: Operating System :: OS Independent
Requires-Python: >=3.6
Requires-Dist: pyyaml>=6.0
Requires-Dist: jinja2>=3.0.0
Dynamic: author
Dynamic: author-email
Dynamic: classifier
Dynamic: description
Dynamic: description-content-type
Dynamic: home-page
Dynamic: requires-dist
Dynamic: requires-python
Dynamic: summary
